setup.py
qiwimaster/__init__.py
qiwimaster/api.py
qiwimaster/exceptions.py
qiwimaster.egg-info/PKG-INFO
qiwimaster.egg-info/SOURCES.txt
qiwimaster.egg-info/dependency_links.txt
qiwimaster.egg-info/requires.txt
qiwimaster.egg-info/top_level.txt