Metadata-Version: 2.1
Name: qiwimaster
Version: 1.0
Summary: qiwimaster
Author: qxtony
